algo_magic/__init__.py
algo_magic/algo_magic.py
algo_magic/dis.py
algo_magic/pep8.py
algo_magic/truth.py
algo_magic/tutor.py
algo_magic-1.3.2.dist-info/LICENSE
algo_magic-1.3.2.dist-info/METADATA
algo_magic-1.3.2.dist-info/WHEEL
algo_magic-1.3.2.dist-info/top_level.txt
algo_magic-1.3.2.dist-info/RECORD
