Metadata-Version: 2.1
Name: algo-magic
Version: 1.3.2
Summary: Set of IPython magic extensions used in the first year algorithmics course at University of Lorraine.
Home-page: https://github.com/laowantong/algo_magic
Author: Aristide Grange
Author-email: name.surname@univ-lorraine.fr
License: MIT
Keywords: algorithmics tools
Platform: UNKNOWN
Classifier: Development Status :: 5 - Production/Stable
Classifier: Intended Audience :: Education
Classifier: Intended Audience :: Information Technology
Classifier: Topic :: Database
Classifier: License :: OSI Approved :: MIT License
Classifier: Programming Language :: Python :: 3
Classifier: Programming Language :: Python :: 3.5
Classifier: Framework :: IPython
Requires-Dist: ipython
Requires-Dist: yapf
